pykmlib.cpython-37m-x86_64-linux-gnu.so
omim_pykmlib.libs/libkrb5-7e4170ab.so.3.3
omim_pykmlib.libs/libcom_err-f79b9776.so.2.1
omim_pykmlib.libs/libicudata-13dff365.so.42.1
omim_pykmlib.libs/libkeyutils-68db41cc.so.1.3
omim_pykmlib.libs/libselinux-d72a37e2.so.1
omim_pykmlib.libs/libQt5Core-0d6f67b3.so.5.6.1
omim_pykmlib.libs/libssl-09014658.so.1.0.1e
omim_pykmlib.libs/libgssapi_krb5-bb73e344.so.2.2
omim_pykmlib.libs/libicui18n-6ab72f54.so.42.1
omim_pykmlib.libs/libz-eb09ad1d.so.1.2.3
omim_pykmlib.libs/libcrypto-142cf8a3.so.1.0.1e
omim_pykmlib.libs/libexpat-c6aed692.so.1.6.11
omim_pykmlib.libs/libk5crypto-ab4ddf4c.so.3.1
omim_pykmlib.libs/libicuuc-8a9b26fa.so.42.1
omim_pykmlib.libs/libkrb5support-2ce1fd50.so.0.1
omim_pykmlib.libs/libQt5Network-ebaa4687.so.5.6.1
omim_pykmlib-10.3.0rc2.dist-info/METADATA
omim_pykmlib-10.3.0rc2.dist-info/WHEEL
omim_pykmlib-10.3.0rc2.dist-info/RECORD
omim_pykmlib-10.3.0rc2.dist-info/top_level.txt
